jupyter_interval_widget/__init__.py
jupyter_interval_widget/_version.py
jupyter_interval_widget/interval.py
jupyter_interval_widget/static/extension.js
jupyter_interval_widget/static/index.js
jupyter_interval_widget/static/index.js.map
jupyter_interval_widget-0.1.1.data/data/etc/jupyter/nbconfig/notebook.d/jupyter-interval-widget.json
jupyter_interval_widget-0.1.1.data/data/share/jupyter/nbextensions/jupyter-interval-widget/extension.js
jupyter_interval_widget-0.1.1.data/data/share/jupyter/nbextensions/jupyter-interval-widget/index.js
jupyter_interval_widget-0.1.1.data/data/share/jupyter/nbextensions/jupyter-interval-widget/index.js.map
jupyter_interval_widget-0.1.1.dist-info/LICENSE
jupyter_interval_widget-0.1.1.dist-info/METADATA
jupyter_interval_widget-0.1.1.dist-info/WHEEL
jupyter_interval_widget-0.1.1.dist-info/top_level.txt
jupyter_interval_widget-0.1.1.dist-info/RECORD
